{
  "cwd": "C:\\xampp\\htdocs\\geo007ERP",
  "type": [
    "cordova",
    "web",
    "pwa"
  ],
  "name": "7P ERP",
  "framework": "core",
  "template": "split-view",
  "bundler": "webpack",
  "cssPreProcessor": false,
  "theming": {
    "customColor": true,
    "color": "#393939",
    "darkTheme": true,
    "iconFonts": true,
    "fillBars": true
  },
  "customBuild": false,
  "webpack": {
    "developmentSourceMap": true,
    "productionSourceMap": true,
    "hashAssets": false,
    "preserveAssetsPaths": false,
    "inlineAssets": true
  },
  "pkg": "io.framework7.myapp",
  "cordova": {
    "folder": "cordova",
    "platforms": [
      "ios",
      "android"
    ],
    "plugins": [
      "cordova-plugin-statusbar",
      "cordova-plugin-keyboard",
      "cordova-plugin-splashscreen"
    ]
  }
}